premovr/__init__.py
premovr/entrypoint.py
premovr/game_interfaces/__init__.py
premovr/game_interfaces/lichess_api.py
premovr/hardware_interfaces/__init__.py
premovr/hardware_interfaces/http_server_api.py
premovr-0.0.5.dist-info/entry_points.txt
premovr-0.0.5.dist-info/WHEEL
premovr-0.0.5.dist-info/METADATA
premovr-0.0.5.dist-info/RECORD
